aroma/__init__.py
aroma/core.py
aroma_py-0.0.1.dist-info/METADATA
aroma_py-0.0.1.dist-info/WHEEL
aroma_py-0.0.1.dist-info/top_level.txt
aroma_py-0.0.1.dist-info/RECORD
