Metadata-Version: 2.1
Name: aroma-py
Version: 0.0.1
Summary: A lightweight Python web framework like Aroma.js
Home-page: https://github.com/aaveshdev/aroma-py
Author: Aavesh Jilani
Author-email: aavesh@dragon-lang.org
License: UNKNOWN
Platform: UNKNOWN
Classifier: Programming Language :: Python :: 3
Classifier: License :: OSI Approved :: MIT License
Classifier: Operating System :: OS Independent
Requires-Python: >=3.6
Requires-Dist: Jinja2>=3.0.0
